[
    {
        "clipTitle": "colinonepingonly",
        "tab": "Colin",
        "imageTitle": "colindrunk",
        "orderInMenu": 100,
        "title": "One ping only"
    },
    {
        "clipTitle": "colinperiscopedownnick",
        "tab": "Colin",
        "imageTitle": "colindrunk",
        "orderInMenu": 200,
        "title": "Periscope down Nick"
    },
    {
        "clipTitle": "kevinlaugh1",
        "tab": "Kevin",
        "imageTitle": "kevinsass",
        "orderInMenu": 300,
        "title": "Kevin Laugh 1"
    },
    {
        "clipTitle": "kevinthatsnothowitworks",
        "tab": "Kevin",
        "imageTitle": "kevinnotinterested",
        "orderInMenu": 400,
        "title": "That's not how it works!"
    },
    {
        "clipTitle": "nickyourehufflepuff",
        "tab": "Nick",
        "imageTitle": "nickprofile",
        "orderInMenu": 500,
        "title": "You're Hufflepuff!"
    },
    {
        "clipTitle": "colinhooo1",
        "tab": "Colin",
        "imageTitle": "colinallowit",
        "orderInMenu": 600,
        "title": "Hooo! 1"
    },
    {
        "clipTitle": "colinhooo2",
        "tab": "Colin",
        "imageTitle": "colinallowit",
        "orderInMenu": 700,
        "title": "Hooo! 2"
    },
    {
        "clipTitle": "colinhooo3",
        "tab": "Colin",
        "imageTitle": "colinallowit",
        "orderInMenu": 800,
        "title": "Hooo! 3"
    },
    {
        "clipTitle": "colinyesbrother",
        "tab": "Colin",
        "imageTitle": "colinbane",
        "orderInMenu": 900,
        "title": "Yes Brother!"
    },
    {
        "clipTitle": "gregabakersdozen",
        "tab": "Greg",
        "imageTitle": "gregprofile",
        "orderInMenu": 1000,
        "title": "A bakers dozen!"
    },
    {
        "clipTitle": "gregandthewaters",
        "tab": "Greg",
        "imageTitle": "greghappy",
        "orderInMenu": 1100,
        "title": "And the waters.. Receded"
    },
    {
        "clipTitle": "nickitsfine",
        "tab": "Nick",
        "imageTitle": "nickamazed",
        "orderInMenu": 1200,
        "title": "Its... Fine"
    },
    {
        "clipTitle": "nickprincescream",
        "tab": "Nick",
        "imageTitle": "nickshower",
        "orderInMenu": 1300,
        "title": "Prince scream"
    },
    {
        "clipTitle": "timkfl2ishappening",
        "tab": "tim",
        "imageTitle": "timohyeah",
        "orderInMenu": 1400,
        "title": "Kinda Funny Live 2.. Is Happening"
    },
    {
        "clipTitle": "timholyshititshappening",
        "tab": "tim",
        "imageTitle": "timohyeah",
        "orderInMenu": 1500,
        "title": "Holy shit its happening!"
    },
    {
        "clipTitle": "timnotlikethis",
        "tab": "tim",
        "imageTitle": "timohyeah",
        "orderInMenu": 1600,
        "title": "Not like this"
    },
    {
        "clipTitle": "timareyouserious",
        "tab": "tim",
        "imageTitle": "timohyeah",
        "orderInMenu": 1700,
        "title": "Are you serious?!"
    },
    {
        "clipTitle": "colinsquarespace",
        "tab": "Colin",
        "imageTitle": "colindrunk",
        "orderInMenu": 1800,
        "title": "Squarespace"
    },
    {
        "clipTitle": "colinbuilditbeautiful",
        "tab": "Colin",
        "imageTitle": "colinallowit",
        "orderInMenu": 1900,
        "title": "Build it, Beautiful"
    },
    {
        "clipTitle": "gregthegameovergreggyshow",
        "tab": "Greg",
        "imageTitle": "gogshow",
        "orderInMenu": 2000,
        "title": "The Game Over Greggy Show"
    },
    {
        "clipTitle": "colinalotofpeople",
        "tab": "Colin",
        "imageTitle": "colindrunk",
        "orderInMenu": 2100,
        "title": "A lot of people in the world, Greg"
    },
    {
        "clipTitle": "gregamillionbridges",
        "tab": "Greg",
        "imageTitle": "greghappy",
        "orderInMenu": 2200,
        "title": "A million bridges"
    },
    {
        "clipTitle": "gregjumpoffabridge",
        "tab": "Greg",
        "imageTitle": "gregprofile",
        "orderInMenu": 2300,
        "title": "Jump off a bridge"
    },
    {
        "clipTitle": "colinidareyou",
        "tab": "Colin",
        "imageTitle": "colindrunk",
        "orderInMenu": 2400,
        "title": "I dare you"
    },
    {
        "clipTitle": "kevinlivesthedream",
        "tab": "Kevin",
        "imageTitle": "kevinsass",
        "orderInMenu": 2500,
        "title": "I live the dream"
    },
    {
        "clipTitle": "nickwerestillonthis",
        "tab": "Nick",
        "imageTitle": "nickamazed",
        "orderInMenu": 2600,
        "title": "We're still on this"
    },
    {
        "clipTitle": "gregareyououtofyourmind",
        "tab": "Greg",
        "imageTitle": "gregbatman",
        "orderInMenu": 2700,
        "title": "Are you out of your mind?"
    },
    {
        "clipTitle": "timitstrue",
        "tab": "tim",
        "imageTitle": "timohyeah",
        "orderInMenu": 2800,
        "title": "It's true"
    },
    {
        "clipTitle": "timdisneyprincesslist",
        "tab": "tim",
        "imageTitle": "timohyeah",
        "orderInMenu": 2900,
        "title": "Disney Princess list"
    },
    {
        "clipTitle": "colinwatchinganant",
        "tab": "Colin",
        "imageTitle": "colinallowit",
        "orderInMenu": 3000,
        "title": "Watching an ant"
    },
    {
        "clipTitle": "nicksquirtlezard",
        "tab": "Nick",
        "imageTitle": "nickamazed",
        "orderInMenu": 3100,
        "title": "Squirtlezard"
    },
    {
        "clipTitle": "kevinitwasajoke",
        "tab": "Kevin",
        "imageTitle": "kevinworried",
        "orderInMenu": 3200,
        "title": "It was a joke."
    },
    {
        "clipTitle": "gregreelingitin",
        "tab": "Greg",
        "imageTitle": "gregbatman",
        "orderInMenu": 3300,
        "title": "Reeling it the fuck in"
    },
    {
        "clipTitle": "greghappiestday",
        "tab": "Greg",
        "imageTitle": "gregbatman",
        "orderInMenu": 3400,
        "title": "Happiest day of my life"
    },
    {
        "clipTitle": "gregmyshiphascomein",
        "tab": "Greg",
        "imageTitle": "gregbatman",
        "orderInMenu": 3500,
        "title": "My ship has come in"
    },
    {
        "clipTitle": "greggrandmamiller",
        "tab": "Greg",
        "imageTitle": "greghappy",
        "orderInMenu": 3600,
        "title": "Grandma Miller & the Sickly Raccoon"
    },
    {
        "clipTitle": "greglaugh1",
        "tab": "Greg",
        "imageTitle": "greghappy",
        "orderInMenu": 3700,
        "title": "Greg Laugh 1"
    },
    {
        "clipTitle": "greglaugh2",
        "tab": "Greg",
        "imageTitle": "greghappy",
        "orderInMenu": 3701,
        "title": "Greg Laugh 2"
    },
    {
        "clipTitle": "greglaugh3",
        "tab": "Greg",
        "imageTitle": "greghappy",
        "orderInMenu": 3702,
        "title": "Greg Laugh 3"
    },
    {
        "clipTitle": "greglaugh4",
        "tab": "Greg",
        "imageTitle": "gregoreo",
        "orderInMenu": 3703,
        "title": "Greg Laugh 4"
    },
    {
        "clipTitle": "gregifimlyinimdyin",
        "tab": "Greg",
        "imageTitle": "greghappy",
        "orderInMenu": 3800,
        "title": "If I'm Lyin' I'm Dyin'"
    },
    {
        "clipTitle": "colinyouredismissed",
        "tab": "Colin",
        "imageTitle": "colinyeahright",
        "orderInMenu": 3900,
        "title": "You're dismissed"
    },
    {
        "clipTitle": "kevingoodminorityreport",
        "tab": "Kevin",
        "imageTitle": "kevinsmart",
        "orderInMenu": 4000,
        "title": "Positive Minority Report"
    },
    {
        "clipTitle": "miscgrapefruittechnique",
        "tab": "Misc",
        "imageTitle": "misclaughing",
        "orderInMenu": 2525,
        "title": "The Grapefruit Technique"
    },
    {
        "clipTitle": "misclaughing",
        "tab": "Misc",
        "imageTitle": "misclaughing",
        "orderInMenu": 2526,
        "title": "KF Laughing"
    },
    {
        "clipTitle": "colinohmygod",
        "tab": "Colin",
        "imageTitle": "colinrelevant",
        "orderInMenu": 4300,
        "title": "Oh my god"
    },
    {
        "clipTitle": "greggoinghome",
        "tab": "Greg",
        "imageTitle": "gregprofile",
        "orderInMenu": 4400,
        "title": "I'm going home"
    },
    {
        "clipTitle": "gregsoftoiguvna",
        "tab": "Greg",
        "imageTitle": "gregbatman",
        "orderInMenu": 1002,
        "title": "Oi Guvna (Soft)"
    },
    {
        "clipTitle": "nicklaugh1",
        "tab": "Nick",
        "imageTitle": "nickshower",
        "orderInMenu": 4600,
        "title": "Nick Laugh 1"
    },
    {
        "clipTitle": "miscwevegotsteveharvey",
        "tab": "Nick",
        "imageTitle": "nickamazed",
        "orderInMenu": 4700,
        "title": "We've got Steve Harvey"
    },
    {
        "clipTitle": "nickthrowfireball",
        "tab": "Nick",
        "imageTitle": "nickprofile",
        "orderInMenu": 4800,
        "title": "Throw a fireball"
    },
    {
        "clipTitle": "nickmagicmissile",
        "tab": "Nick",
        "imageTitle": "nickprofile",
        "orderInMenu": 4900,
        "title": "Magic Missile"
    },
    {
        "clipTitle": "timyougotsmatteredbro",
        "tab": "tim",
        "imageTitle": "timohyeah",
        "orderInMenu": 5000,
        "title": "You got smattered, Bro"
    },
    {
        "clipTitle": "kevinscyther",
        "tab": "Kevin",
        "imageTitle": "kevinsass",
        "orderInMenu": 5100,
        "title": "Stop what you are doing"
    },
    {
        "clipTitle": "gregfancysidewalks",
        "tab": "Greg",
        "imageTitle": "greghappy",
        "orderInMenu": 5200,
        "title": "Fancy people with sidewalks"
    },
    {
        "clipTitle": "colinwaterman1",
        "tab": "Colin",
        "imageTitle": "colinbemused",
        "orderInMenu": 5300,
        "title": "The Water Man #1"
    },
    {
        "clipTitle": "colinwaterman2",
        "tab": "Colin",
        "imageTitle": "colinbemused",
        "orderInMenu": 5301,
        "title": "The Water Man #2"
    },
    {
        "clipTitle": "colinwaterman3",
        "tab": "Colin",
        "imageTitle": "colinbemused",
        "orderInMenu": 5302,
        "title": "The Water Man #3"
    },
    {
        "clipTitle": "colinwaterman4",
        "tab": "Colin",
        "imageTitle": "colinbemused",
        "orderInMenu": 5304,
        "title": "The Water Man #4"
    },
    {
        "clipTitle": "colintimetogomobile",
        "tab": "Colin",
        "imageTitle": "colinbane",
        "orderInMenu": 5400,
        "title": "Time to go mobile"
    },
    {
        "clipTitle": "gregproducerseducer1",
        "tab": "Greg",
        "imageTitle": "gregprofile",
        "orderInMenu": 5500,
        "title": "The Producer / Seducer 1"
    },
    {
        "clipTitle": "colinimingoodspirits",
        "tab": "Colin",
        "imageTitle": "colinallowit",
        "orderInMenu": 5600,
        "title": "I'm in good spirits"
    },
    {
        "clipTitle": "timlaugh1",
        "tab": "tim",
        "imageTitle": "timlaughscream",
        "orderInMenu": 5700,
        "title": "Tim Laugh 1"
    },
    {
        "clipTitle": "gregonetwothree",
        "tab": "Greg",
        "imageTitle": "gregoreo",
        "orderInMenu": 5800,
        "title": "One, two, threee"
    },
    {
        "clipTitle": "gregpresscharges",
        "tab": "Greg",
        "imageTitle": "gregoreo",
        "orderInMenu": 5900,
        "title": "Press charges"
    },
    {
        "clipTitle": "gregslipperycream",
        "tab": "Greg",
        "imageTitle": "gregoreo",
        "orderInMenu": 6000,
        "title": "Slippery Cream"
    },
    {
        "clipTitle": "gregaroughgoofit",
        "tab": "Greg",
        "imageTitle": "gregoreo",
        "orderInMenu": 6100,
        "title": "A rough go of it"
    },
    {
        "clipTitle": "gregbeabitreasonable",
        "tab": "Greg",
        "imageTitle": "gregoreo",
        "orderInMenu": 6200,
        "title": "Be a bit reasonable"
    },
    {
        "clipTitle": "colinshuhei",
        "tab": "Colin",
        "imageTitle": "colinpepper",
        "orderInMenu": 6300,
        "title": "SHUHEI!"
    },
    {
        "clipTitle": "miscscreaming",
        "tab": "Misc",
        "imageTitle": "kevinfire",
        "orderInMenu": 4201,
        "title": "KF Screaming"
    },
    {
        "clipTitle": "kevinihateyouguys",
        "tab": "Kevin",
        "imageTitle": "kevinsass",
        "orderInMenu": 6400,
        "title": "I hate you Guys"
    },
    {
        "clipTitle": "kevinohgod",
        "tab": "Kevin",
        "imageTitle": "kevinfire",
        "orderInMenu": 6500,
        "title": "Oh god!"
    },
    {
        "clipTitle": "nickprincescreamlong",
        "tab": "Nick",
        "imageTitle": "nickshower",
        "orderInMenu": 1301,
        "title": "Prince scream (Longer)"
    },
    {
        "clipTitle": "colinalifedebt",
        "tab": "Colin",
        "imageTitle": "colinallowit",
        "orderInMenu": 6600,
        "title": "A life debt"
    },
    {
        "clipTitle": "gregoi",
        "tab": "Greg",
        "imageTitle": "gregprofile",
        "orderInMenu": 1001,
        "title": "Oi!"
    },
    {
        "clipTitle": "nicksuperman",
        "tab": "Nick",
        "imageTitle": "nickamazed",
        "orderInMenu": 6700,
        "title": "Superman!"
    },
    {
        "clipTitle": "nickkevinonthetwentyseventh",
        "tab": "Nick",
        "imageTitle": "nickbusted",
        "orderInMenu": 6800,
        "title": "Kevin on the 27th"
    },
    {
        "clipTitle": "nickdoesyourgirlfriend",
        "tab": "Nick",
        "imageTitle": "nickamazed",
        "orderInMenu": 6900,
        "title": "Does your Girlfriend?"
    },
    {
        "clipTitle": "nickthatsinsidious",
        "tab": "Nick",
        "imageTitle": "nickbusted",
        "orderInMenu": 7000,
        "title": "Thats insidious"
    },
    {
        "clipTitle": "nicktooktherice",
        "tab": "Nick",
        "imageTitle": "nickbusted",
        "orderInMenu": 7100,
        "title": "You took the rice..."
    },
    {
        "clipTitle": "colinkevindoesit",
        "tab": "Colin",
        "imageTitle": "colindrunk",
        "orderInMenu": 7200,
        "title": "When Kevin does it"
    },
    {
        "clipTitle": "colintouchmeagain",
        "tab": "Colin",
        "imageTitle": "colindrunk",
        "orderInMenu": 7300,
        "title": "Touch me again"
    },
    {
        "clipTitle": "kevinmorepizza",
        "tab": "Kevin",
        "imageTitle": "kevinsass",
        "orderInMenu": 7400,
        "title": "Sorry for trying"
    },
    {
        "clipTitle": "timifthisisacareer",
        "tab": "tim",
        "imageTitle": "timsleeping",
        "orderInMenu": 7500,
        "title": "If this is a career..."
    },
    {
        "clipTitle": "nickkilledsomeone",
        "tab": "Nick",
        "imageTitle": "nickprofile",
        "orderInMenu": 7600,
        "title": "He killed someone"
    },
    {
        "clipTitle": "nicksexforthefirsttime",
        "tab": "Nick",
        "imageTitle": "nickprofile",
        "orderInMenu": 7700,
        "title": "Sex for the first time"
    },
    {
        "clipTitle": "gregcoupleofbucks",
        "tab": "Greg",
        "imageTitle": "greghappy",
        "orderInMenu": 7800,
        "title": "Couple of Bucks"
    },
    {
        "clipTitle": "colindoesntforget",
        "tab": "Colin",
        "imageTitle": "colinrelevant",
        "orderInMenu": 7900,
        "title": "Colin doesn't forget"
    },
    {
        "clipTitle": "colinnameinanotebook",
        "tab": "Colin",
        "imageTitle": "colinbemused",
        "orderInMenu": 8000,
        "title": "Name in a notebook"
    },
    {
        "clipTitle": "colinopenthebook",
        "tab": "Colin",
        "imageTitle": "colinworried",
        "orderInMenu": 8100,
        "title": "I open the book..."
    },
    {
        "clipTitle": "colinenjoyit",
        "tab": "Colin",
        "imageTitle": "colinlovesyou",
        "orderInMenu": 8200,
        "title": "I masturbate to it"
    },
    {
        "clipTitle": "nickbongoslong",
        "tab": "Nick",
        "imageTitle": "nickbongos",
        "orderInMenu": 8400,
        "title": "BONGOS! (Long) 1"
    },
    {
        "clipTitle": "nickbongos1",
        "tab": "Nick",
        "imageTitle": "nickbongos",
        "orderInMenu": 8300,
        "title": "BONGOS! 1"
    },
    {
        "clipTitle": "colindrmoriarty",
        "tab": "Colin",
        "imageTitle": "colinallowit",
        "orderInMenu": 8500,
        "title": "Dr. Moriarty"
    },
    {
        "clipTitle": "colintenfeethigher",
        "tab": "Colin",
        "imageTitle": "colinrelevant",
        "orderInMenu": 8600,
        "title": "The wall"
    },
    {
        "clipTitle": "colinwouldyourather",
        "tab": "Colin",
        "imageTitle": "colinpepper",
        "orderInMenu": 8700,
        "title": "Would you rather?"
    },
    {
        "clipTitle": "kevinrubbedmybelly",
        "tab": "Kevin",
        "imageTitle": "kevinworried",
        "orderInMenu": 8800,
        "title": "Slapped my little tummy"
    },
    {
        "clipTitle": "miscimmigrantsong",
        "tab": "Misc",
        "imageTitle": "misclaughing",
        "orderInMenu": 8900,
        "title": "Immigrant Song"
    },
    {
        "clipTitle": "gregthefemalepersuasion",
        "tab": "Greg",
        "imageTitle": "gregprofile",
        "orderInMenu": 9000,
        "title": "Thank you ladies"
    },
    {
        "clipTitle": "nickguaranteed",
        "tab": "Nick",
        "imageTitle": "nicklick",
        "orderInMenu": 9100,
        "title": "Buttholes next time"
    },
    {
        "clipTitle": "nickaerobicssong",
        "tab": "Nick",
        "imageTitle": "nickprofile2",
        "orderInMenu": 9200,
        "title": "Aerobics song"
    },
    {
        "clipTitle": "gregpaulasister",
        "tab": "Greg",
        "imageTitle": "gregoreo",
        "orderInMenu": 9300,
        "title": "Paula's your sister?!"
    },
    {
        "clipTitle": "miscdonttelltim",
        "tab": "Misc",
        "imageTitle": "misclaughing",
        "orderInMenu": 9400,
        "title": "Tim doesn't play games?"
    },
    {
        "clipTitle": "nickbigkevdog",
        "tab": "Nick",
        "imageTitle": "nickamazed",
        "orderInMenu": 9500,
        "title": "Big Kev Dog!"
    },
    {
        "clipTitle": "nickbongoslong2",
        "tab": "Nick",
        "imageTitle": "nickbongos",
        "orderInMenu": 8401,
        "title": "BONGOS! (Long) 2"
    },
    {
        "clipTitle": "nickbongoslong3",
        "tab": "Nick",
        "imageTitle": "nickbongos",
        "orderInMenu": 8402,
        "title": "BONGOS! (Long) 3"
    },
    {
        "clipTitle": "nickbongos2",
        "tab": "Nick",
        "imageTitle": "nickbongos",
        "orderInMenu": 8301,
        "title": "BONGOS! 2"
    },
    {
        "clipTitle": "nickbongos3",
        "tab": "Nick",
        "imageTitle": "nickbongos",
        "orderInMenu": 8302,
        "title": "BONGOS! 3"
    },
    {
        "clipTitle": "timhasfinalfantasyxv",
        "tab": "tim",
        "imageTitle": "timlaughscream",
        "orderInMenu": 9600,
        "title": "Tim has FFXV"
    },
    {
        "clipTitle": "colinshout1",
        "tab": "Colin",
        "imageTitle": "colinpepper",
        "orderInMenu": 9700,
        "title": "Colin Shout 1"
    },
    {
        "clipTitle": "timlaugh2",
        "tab": "tim",
        "imageTitle": "timlaughscream",
        "orderInMenu": 5701,
        "title": "Tim Laugh 2"
    },
    {
        "clipTitle": "colingregcantbeon",
        "tab": "Colin",
        "imageTitle": "colinbane",
        "orderInMenu": 9800,
        "title": "Get rid of Greg"
    },
    {
        "clipTitle": "timlaugh3",
        "tab": "tim",
        "imageTitle": "timlaughscream",
        "orderInMenu": 5702,
        "title": "Tim Laugh 3"
    },
    {
        "clipTitle": "timlaugh4",
        "tab": "tim",
        "imageTitle": "timlaughscream",
        "orderInMenu": 5703,
        "title": "Tim Laugh 4"
    },
    {
        "clipTitle": "kevinheatupthatrag",
        "tab": "Kevin",
        "imageTitle": "kevinsass",
        "orderInMenu": 9900,
        "title": "Shave Tim"
    },
    {
        "clipTitle": "miscgameovergreggyshow",
        "tab": "Misc",
        "imageTitle": "gogshow",
        "orderInMenu": 10000,
        "title": "Game Over Greggy Show Theme"
    },
    {
        "clipTitle": "miscgamescasttheme",
        "tab": "Misc",
        "imageTitle": "kfgamescast",
        "orderInMenu": 10100,
        "title": "Gamescast Theme"
    },
    {
        "clipTitle": "miscpsiloveyou",
        "tab": "Misc",
        "imageTitle": "psiloveyou",
        "orderInMenu": 10200,
        "title": "PS I Love You Theme"
    }
]